phys2cvr/__init__.py
phys2cvr/_version.py
phys2cvr/io.py
phys2cvr/regressors.py
phys2cvr/signal.py
phys2cvr/stats.py
phys2cvr/utils.py
phys2cvr/viz.py
phys2cvr/workflows.py
phys2cvr/cli/__init__.py
phys2cvr/cli/run.py
phys2cvr/tests/__init__.py
phys2cvr/tests/conftest.py
phys2cvr/tests/test_io.py
phys2cvr/tests/test_signal.py
phys2cvr/tests/test_stats.py
phys2cvr-0.28.0.dist-info/licenses/LICENSE
phys2cvr-0.28.0.dist-info/METADATA
phys2cvr-0.28.0.dist-info/WHEEL
phys2cvr-0.28.0.dist-info/entry_points.txt
phys2cvr-0.28.0.dist-info/top_level.txt
phys2cvr-0.28.0.dist-info/RECORD
