Metadata-Version: 2.4
Name: phys2cvr
Version: 0.28.0
Summary: Python library to generate regressors for and compute Cerebrovascular Reactivity and lag maps.
Home-page: https://github.com/smoia/phys2cvr
Download-URL: https://github.com/smoia/phys2cvr
Author: Stefano Moia
Maintainer: Stefano Moia
Maintainer-email: s.moia.research@gmail.com
License: Apache-2.0
Platform: OS Independent
Classifier: Development Status :: 4 - Beta
Classifier: Intended Audience :: Science/Research
Classifier: License :: OSI Approved :: Apache Software License
Classifier: Programming Language :: Python :: 3.8
Classifier: Programming Language :: Python :: 3.9
Classifier: Programming Language :: Python :: 3.10
Classifier: Programming Language :: Python :: 3.11
Classifier: Programming Language :: Python :: 3.12
Classifier: Programming Language :: Python :: 3.13
Provides: phys2cvr
Requires-Python: >=3.6.1
License-File: LICENSE
Requires-Dist: numpy>=1.20.0
Requires-Dist: matplotlib>=3.1.1
Requires-Dist: nibabel
Requires-Dist: scipy
Requires-Dist: peakdet
Provides-Extra: responses
Requires-Dist: phys2denoise; extra == "responses"
Provides-Extra: matlab
Requires-Dist: pymatreader; extra == "matlab"
Provides-Extra: doc
Requires-Dist: sphinx>=2.0; extra == "doc"
Requires-Dist: sphinx-argparse; extra == "doc"
Requires-Dist: sphinx_rtd_theme; extra == "doc"
Requires-Dist: myst-parser; extra == "doc"
Provides-Extra: style
Requires-Dist: codespell>=2.2.4; extra == "style"
Requires-Dist: ruff>=0.14.2; extra == "style"
Provides-Extra: test
Requires-Dist: phys2denoise; extra == "test"
Requires-Dist: pymatreader; extra == "test"
Requires-Dist: codespell>=2.2.4; extra == "test"
Requires-Dist: ruff>=0.14.2; extra == "test"
Requires-Dist: pytest-cov; extra == "test"
Requires-Dist: coverage; extra == "test"
Provides-Extra: devtools
Requires-Dist: pre-commit; extra == "devtools"
Provides-Extra: dev
Requires-Dist: pre-commit; extra == "dev"
Requires-Dist: sphinx>=2.0; extra == "dev"
Requires-Dist: sphinx-argparse; extra == "dev"
Requires-Dist: sphinx_rtd_theme; extra == "dev"
Requires-Dist: myst-parser; extra == "dev"
Requires-Dist: phys2denoise; extra == "dev"
Requires-Dist: pymatreader; extra == "dev"
Requires-Dist: codespell>=2.2.4; extra == "dev"
Requires-Dist: ruff>=0.14.2; extra == "dev"
Requires-Dist: pytest-cov; extra == "dev"
Requires-Dist: coverage; extra == "dev"
Dynamic: download-url
Dynamic: license-file
Dynamic: provides
